custom_sidebar_icons/__init__.py
Sidebar_nav_custom_icons_streamlit-0.0.7.dist-info/LICENSE
Sidebar_nav_custom_icons_streamlit-0.0.7.dist-info/METADATA
Sidebar_nav_custom_icons_streamlit-0.0.7.dist-info/WHEEL
Sidebar_nav_custom_icons_streamlit-0.0.7.dist-info/top_level.txt
Sidebar_nav_custom_icons_streamlit-0.0.7.dist-info/RECORD
