Metadata-Version: 2.1
Name: Sidebar-nav-custom-icons-streamlit
Version: 0.0.7
Summary: Streamlit component that allows you to set emojis from 5 prettier icon libraries
Home-page: 
Author: 
Author-email: 
Requires-Python: >=3.7
License-File: LICENSE
Requires-Dist: streamlit (>=0.63)
